pydevdtk/__init__.py
pydevdtk/version.py
pydevdtk/coms/__init__.py
pydevdtk/coms/ble.py
pydevdtk/coms/serial.py
pydevdtk/plotting/__init__.py
pydevdtk/plotting/plotter.py
pydevdtk/plotting/plotter_base.py
pydevdtk/plotting/plotter_manager.py
pydevdtk-0.1.1.dist-info/METADATA
pydevdtk-0.1.1.dist-info/WHEEL
pydevdtk-0.1.1.dist-info/licenses/LICENSE
pydevdtk-0.1.1.dist-info/RECORD
