Metadata-Version: 2.3
Name: PyDevDTK
Version: 0.1.1
Summary: Python device development toolkit
Project-URL: Homepage, https://github.com/BojanSof/pydevdtk
Project-URL: Bug Tracker, https://github.com/BojanSof/pydevdtk/issues
Author-email: Bojan Sofronievski <bojan.drago@gmail.com>
License-File: LICENSE
Classifier: License :: OSI Approved :: MIT License
Classifier: Operating System :: OS Independent
Classifier: Programming Language :: Python :: 3
Requires-Python: >=3.10
Requires-Dist: matplotlib>=3.5.2
Requires-Dist: numpy>=1.23.3
